quipus/__init__.py
quipus/data_sources/__init__.py
quipus/data_sources/csv_data_source.py
quipus/data_sources/csv_source.py
quipus/data_sources/data_source.py
quipus/data_sources/database_source.py
quipus/data_sources/file_source.py
quipus/data_sources/mongo_source.py
quipus/data_sources/mysql_source.py
quipus/data_sources/parquet_source.py
quipus/data_sources/postgre_source.py
quipus/data_sources/xlsx_source.py
quipus/models/__init__.py
quipus/models/template.py
quipus/services/__init__.py
quipus/services/s3_delivery.py
quipus/services/sftp_delivery.py
quipus/services/smtp_delivery.py
quipus/services/template_manager.py
quipus/utils/__init__.py
quipus/utils/connectable.py
quipus/utils/dbconfig.py
quipus/utils/types.py
quipus-0.4.0.dist-info/LICENSE
quipus-0.4.0.dist-info/METADATA
quipus-0.4.0.dist-info/WHEEL
quipus-0.4.0.dist-info/RECORD
