Metadata-Version: 2.3
Name: quipus
Version: 0.4.0
Summary: Data retrieval, template manager and delivery all in one!
License: GPL-3.0
Author: Jorge U. Alarcón
Author-email: j1dev@proton.me
Requires-Python: >=3.12,<4.0
Classifier: License :: OSI Approved :: GNU General Public License v3 (GPLv3)
Classifier: Programming Language :: Python :: 3
Classifier: Programming Language :: Python :: 3.12
Classifier: Programming Language :: Python :: 3.13
Requires-Dist: XlsxWriter (>=3.2.0,<4.0.0)
Requires-Dist: boto3 (>=1.35.34,<2.0.0)
Requires-Dist: fastexcel (>=0.12.0,<0.13.0)
Requires-Dist: mysql-connector-python (>=9.1.0,<10.0.0)
Requires-Dist: openpyxl (>=3.1.5,<4.0.0)
Requires-Dist: pandas (>=2.2.3,<3.0.0)
Requires-Dist: paramiko (==3.4.1)
Requires-Dist: polars (>=1.12.0,<2.0.0)
Requires-Dist: psycopg (>=3.2.3,<4.0.0)
Requires-Dist: psycopg-pool (>=3.2.3,<4.0.0)
Requires-Dist: pymongo (>=4.10.1,<5.0.0)
Requires-Dist: weasyprint (==62.3)
